spatial_math_mini/SE3.py
spatial_math_mini/SO3.py
spatial_math_mini/__init__.py
spatial_math_mini/base.py
spatial_math_mini/visualize.py
tests/__init__.py
tests/test.py
spatial_math_mini-0.1.3.7.dist-info/METADATA
spatial_math_mini-0.1.3.7.dist-info/WHEEL
spatial_math_mini-0.1.3.7.dist-info/top_level.txt
spatial_math_mini-0.1.3.7.dist-info/RECORD
