Metadata-Version: 2.1
Name: spatial-math-mini
Version: 0.1.3.7
Summary: Python Module for spatial math with minimum dependency
Home-page: https://github.com/kh11kim/spatial_math_mini
Author: Kanghyun Kim
Author-email: kh11kim@kaist.ac.kr
License: UNKNOWN
Keywords: spatial_math_mini
Platform: UNKNOWN
Classifier: Programming Language :: Python
Requires-Python: >=3
Requires-Dist: matplotlib (>=3.5)
Requires-Dist: numpy
